datasetvisualizer/Dataset.py
datasetvisualizer/__init__.py
datasetvisualizer/cli.py
datasetvisualizer/preview.py
datasetvisualizer/custom_components/goto.meta
datasetvisualizer/custom_components/imageselector.meta
datasetvisualizer/custom_components/itemselector.meta
datasetvisualizer/custom_components/itemselectorzoom.meta
datasetvisualizer/custom_components/jsonviewer.meta
datasetvisualizer/custom_components/pageselector.meta
datasetvisualizer/custom_components/slider.meta
datasetvisualizer/custom_components/goto/build.meta
datasetvisualizer/custom_components/goto/build/asset-manifest.json
datasetvisualizer/custom_components/goto/build/asset-manifest.json.meta
datasetvisualizer/custom_components/goto/build/index.html
datasetvisualizer/custom_components/goto/build/index.html.meta
datasetvisualizer/custom_components/goto/build/precache-manifest.4934c8bf5a0af636b4a6779285e3dac4.js
datasetvisualizer/custom_components/goto/build/precache-manifest.4934c8bf5a0af636b4a6779285e3dac4.js.meta
datasetvisualizer/custom_components/goto/build/service-worker.js
datasetvisualizer/custom_components/goto/build/service-worker.js.meta
datasetvisualizer/custom_components/goto/build/static.meta
datasetvisualizer/custom_components/goto/build/static/js.meta
datasetvisualizer/custom_components/goto/build/static/js/2.ec64108f.chunk.js
datasetvisualizer/custom_components/goto/build/static/js/2.ec64108f.chunk.js.LICENSE.txt
datasetvisualizer/custom_components/goto/build/static/js/2.ec64108f.chunk.js.LICENSE.txt.meta
datasetvisualizer/custom_components/goto/build/static/js/2.ec64108f.chunk.js.map
datasetvisualizer/custom_components/goto/build/static/js/2.ec64108f.chunk.js.map.meta
datasetvisualizer/custom_components/goto/build/static/js/2.ec64108f.chunk.js.meta
datasetvisualizer/custom_components/goto/build/static/js/main.19a900a8.chunk.js
datasetvisualizer/custom_components/goto/build/static/js/main.19a900a8.chunk.js.map
unity_cv_datasetvisualizer-0.1.2.dist-info/LICENSE
unity_cv_datasetvisualizer-0.1.2.dist-info/METADATA
unity_cv_datasetvisualizer-0.1.2.dist-info/WHEEL
unity_cv_datasetvisualizer-0.1.2.dist-info/entry_points.txt
unity_cv_datasetvisualizer-0.1.2.dist-info/top_level.txt
unity_cv_datasetvisualizer-0.1.2.dist-info/RECORD
