Metadata-Version: 2.1
Name: unity-cv-datasetvisualizer
Version: 0.1.2
Summary: This Python based tool allows you to visualize datasets created using Unity Computer Vision tools.
Home-page: https://github.com/Unity-Technologies/com.unity.cv.datasetvisualizer
Author: Unity Technologies
License: UNKNOWN
Platform: UNKNOWN
Classifier: Programming Language :: Python :: 3
Classifier: Programming Language :: Python :: 3.7
Classifier: Programming Language :: Python :: 3.8
Classifier: License :: OSI Approved :: Apache Software License
Classifier: Operating System :: MacOS
Classifier: Operating System :: Microsoft :: Windows :: Windows 10
Requires-Python: >=3.7, !=3.9.*
License-File: LICENSE
Requires-Dist: Pillow (>=8.1.0)
Requires-Dist: streamlit (==0.84.1)
Requires-Dist: pyquaternion (>=0.9.9)
Requires-Dist: datasetinsights (==1.1.1)
Requires-Dist: PySide2 (==5.15.2)
